{"v":4,"entries":{"clickablejson--docs":{"id":"clickablejson--docs","title":"ClickableJson","name":"Docs","importPath":"./src/ClickableJson/index.stories.tsx","type":"docs","tags":["autodocs","docs"],"storiesImports":[]},"clickablejson--primary":{"type":"story","id":"clickablejson--primary","name":"Primary","title":"ClickableJson","importPath":"./src/ClickableJson/index.stories.tsx","tags":["autodocs","story"]},"clickablejson--readonly":{"type":"story","id":"clickablejson--readonly","name":"Readonly","title":"ClickableJson","importPath":"./src/ClickableJson/index.stories.tsx","tags":["autodocs","story"]},"clickablejson--formal-and-compact":{"type":"story","id":"clickablejson--formal-and-compact","name":"Formal And Compact","title":"ClickableJson","importPath":"./src/ClickableJson/index.stories.tsx","tags":["autodocs","story"]},"clickablejson--interactive":{"type":"story","id":"clickablejson--interactive","name":"Interactive","title":"ClickableJson","importPath":"./src/ClickableJson/index.stories.tsx","tags":["autodocs","story"]},"clickablejson--interactive-empty":{"type":"story","id":"clickablejson--interactive-empty","name":"Interactive Empty","title":"ClickableJson","importPath":"./src/ClickableJson/index.stories.tsx","tags":["autodocs","story"]},"clickablejson--interactive-large":{"type":"story","id":"clickablejson--interactive-large","name":"Interactive Large","title":"ClickableJson","importPath":"./src/ClickableJson/index.stories.tsx","tags":["autodocs","story"]},"clickablejson--collapsed":{"type":"story","id":"clickablejson--collapsed","name":"Collapsed","title":"ClickableJson","importPath":"./src/ClickableJson/index.stories.tsx","tags":["autodocs","story"]},"clickablejson--binary":{"type":"story","id":"clickablejson--binary","name":"Binary","title":"ClickableJson","importPath":"./src/ClickableJson/index.stories.tsx","tags":["autodocs","story"]},"clickablejsoncrdt--docs":{"id":"clickablejsoncrdt--docs","title":"ClickableJsonCrdt","name":"Docs","importPath":"./src/ClickableJsonCrdt/index.stories.tsx","type":"docs","tags":["autodocs","docs"],"storiesImports":[]},"clickablejsoncrdt--primary":{"type":"story","id":"clickablejsoncrdt--primary","name":"Primary","title":"ClickableJsonCrdt","importPath":"./src/ClickableJsonCrdt/index.stories.tsx","tags":["autodocs","story"]},"clickablejsoncrdt--show-root":{"type":"story","id":"clickablejsoncrdt--show-root","name":"Show Root","title":"ClickableJsonCrdt","importPath":"./src/ClickableJsonCrdt/index.stories.tsx","tags":["autodocs","story"]},"clickablejsoncrdt--interactive-large":{"type":"story","id":"clickablejsoncrdt--interactive-large","name":"Interactive Large","title":"ClickableJsonCrdt","importPath":"./src/ClickableJsonCrdt/index.stories.tsx","tags":["autodocs","story"]},"clickablejsoncrdt--empty-doc":{"type":"story","id":"clickablejsoncrdt--empty-doc","name":"Empty Doc","title":"ClickableJsonCrdt","importPath":"./src/ClickableJsonCrdt/index.stories.tsx","tags":["autodocs","story"]},"clickablejsoncrdt--constant-root":{"type":"story","id":"clickablejsoncrdt--constant-root","name":"Constant Root","title":"ClickableJsonCrdt","importPath":"./src/ClickableJsonCrdt/index.stories.tsx","tags":["autodocs","story"]},"clickablejsoncrdt--constant-root-json":{"type":"story","id":"clickablejsoncrdt--constant-root-json","name":"Constant Root Json","title":"ClickableJsonCrdt","importPath":"./src/ClickableJsonCrdt/index.stories.tsx","tags":["autodocs","story"]},"clickablejsoncrdt--long-values":{"type":"story","id":"clickablejsoncrdt--long-values","name":"Long Values","title":"ClickableJsonCrdt","importPath":"./src/ClickableJsonCrdt/index.stories.tsx","tags":["autodocs","story"]},"jsonatom--docs":{"id":"jsonatom--docs","title":"JsonAtom","name":"Docs","importPath":"./src/JsonAtom/index.stories.tsx","type":"docs","tags":["autodocs","docs"],"storiesImports":[]},"jsonatom--string":{"type":"story","id":"jsonatom--string","name":"String","title":"JsonAtom","importPath":"./src/JsonAtom/index.stories.tsx","tags":["autodocs","story"]},"jsonatom--number":{"type":"story","id":"jsonatom--number","name":"Number","title":"JsonAtom","importPath":"./src/JsonAtom/index.stories.tsx","tags":["autodocs","story"]},"jsonatom--negative-number":{"type":"story","id":"jsonatom--negative-number","name":"Negative Number","title":"JsonAtom","importPath":"./src/JsonAtom/index.stories.tsx","tags":["autodocs","story"]},"jsonatom--float":{"type":"story","id":"jsonatom--float","name":"Float","title":"JsonAtom","importPath":"./src/JsonAtom/index.stories.tsx","tags":["autodocs","story"]},"jsonatom--negative-float":{"type":"story","id":"jsonatom--negative-float","name":"Negative Float","title":"JsonAtom","importPath":"./src/JsonAtom/index.stories.tsx","tags":["autodocs","story"]},"jsonatom--zero":{"type":"story","id":"jsonatom--zero","name":"Zero","title":"JsonAtom","importPath":"./src/JsonAtom/index.stories.tsx","tags":["autodocs","story"]},"jsonatom--null":{"type":"story","id":"jsonatom--null","name":"Null","title":"JsonAtom","importPath":"./src/JsonAtom/index.stories.tsx","tags":["autodocs","story"]},"jsonatom--undefined":{"type":"story","id":"jsonatom--undefined","name":"Undefined","title":"JsonAtom","importPath":"./src/JsonAtom/index.stories.tsx","tags":["autodocs","story"]},"jsonatom--true":{"type":"story","id":"jsonatom--true","name":"True","title":"JsonAtom","importPath":"./src/JsonAtom/index.stories.tsx","tags":["autodocs","story"]},"jsonatom--false":{"type":"story","id":"jsonatom--false","name":"False","title":"JsonAtom","importPath":"./src/JsonAtom/index.stories.tsx","tags":["autodocs","story"]},"jsonatom--array":{"type":"story","id":"jsonatom--array","name":"Array","title":"JsonAtom","importPath":"./src/JsonAtom/index.stories.tsx","tags":["autodocs","story"]},"jsonatom--object":{"type":"story","id":"jsonatom--object","name":"Object","title":"JsonAtom","importPath":"./src/JsonAtom/index.stories.tsx","tags":["autodocs","story"]},"jsonatom--binary":{"type":"story","id":"jsonatom--binary","name":"Binary","title":"JsonAtom","importPath":"./src/JsonAtom/index.stories.tsx","tags":["autodocs","story"]},"objectlayout--docs":{"id":"objectlayout--docs","title":"ObjectLayout","name":"Docs","importPath":"./src/ObjectLayout/index.stories.tsx","type":"docs","tags":["autodocs","docs"],"storiesImports":[]},"objectlayout--primary":{"type":"story","id":"objectlayout--primary","name":"Primary","title":"ObjectLayout","importPath":"./src/ObjectLayout/index.stories.tsx","tags":["autodocs","story"]},"input-binding-demo--input":{"type":"story","id":"input-binding-demo--input","name":"Input","title":"Input Binding Demo","importPath":"./src/json-crdt-bindings/index.stories.tsx","tags":["story"]},"input-binding-demo--textarea":{"type":"story","id":"input-binding-demo--textarea","name":"Textarea","title":"Input Binding Demo","importPath":"./src/json-crdt-bindings/index.stories.tsx","tags":["story"]}}}
